py_micro/model/__init__.py
py_micro/model/auth_service_pb2.py
py_micro/model/auth_service_pb2.pyi
py_micro/model/auth_service_pb2_grpc.py
py_micro/model/template_service_pb2.py
py_micro/model/template_service_pb2.pyi
py_micro/model/template_service_pb2_grpc.py
py_micro/model/user_service_pb2.py
py_micro/model/user_service_pb2.pyi
py_micro/model/user_service_pb2_grpc.py
py_micro_models-1.0.0.dist-info/METADATA
py_micro_models-1.0.0.dist-info/WHEEL
py_micro_models-1.0.0.dist-info/RECORD
